gstreamer_runtime-1.27.90.data/purelib/gstreamer_runtime/__init__.py
gstreamer_runtime-1.27.90.data/purelib/gstreamer_runtime/bin/bz2.dll
gstreamer_runtime-1.27.90.data/purelib/gstreamer_runtime/bin/cairo-2.dll
gstreamer_runtime-1.27.90.data/purelib/gstreamer_runtime/bin/cairo-gobject-2.dll
gstreamer_runtime-1.27.90.data/purelib/gstreamer_runtime/bin/cairo-script-interpreter-2.dll
gstreamer_runtime-1.27.90.data/purelib/gstreamer_runtime/bin/dav1d.dll
gstreamer_runtime-1.27.90.data/purelib/gstreamer_runtime/bin/ffi-7.dll
gstreamer_runtime-1.27.90.data/purelib/gstreamer_runtime/bin/fontconfig-1.dll
gstreamer_runtime-1.27.90.data/purelib/gstreamer_runtime/bin/freetype-6.dll
gstreamer_runtime-1.27.90.data/purelib/gstreamer_runtime/bin/fribidi-0.dll
gstreamer_runtime-1.27.90.data/purelib/gstreamer_runtime/bin/gdbus.exe
gstreamer_runtime-1.27.90.data/purelib/gstreamer_runtime/bin/gdk-pixbuf-csource.exe
gstreamer_runtime-1.27.90.data/purelib/gstreamer_runtime/bin/gdk-pixbuf-query-loaders.exe
gstreamer_runtime-1.27.90.data/purelib/gstreamer_runtime/bin/gdk_pixbuf-2.0-0.dll
gstreamer_runtime-1.27.90.data/purelib/gstreamer_runtime/bin/gio-2.0-0.dll
gstreamer_runtime-1.27.90.data/purelib/gstreamer_runtime/bin/gio-querymodules.exe
gstreamer_runtime-1.27.90.data/purelib/gstreamer_runtime/bin/girepository-1.0-1.dll
gstreamer_runtime-1.27.90.data/purelib/gstreamer_runtime/bin/glib-2.0-0.dll
gstreamer_runtime-1.27.90.data/purelib/gstreamer_runtime/bin/glib-compile-schemas.exe
gstreamer_runtime-1.27.90.data/purelib/gstreamer_runtime/bin/gmodule-2.0-0.dll
gstreamer_runtime-1.27.90.data/purelib/gstreamer_runtime/bin/gobject-2.0-0.dll
gstreamer_runtime-1.27.90.data/purelib/gstreamer_runtime/bin/graphene-1.0-0.dll
gstreamer_runtime-1.27.90.data/purelib/gstreamer_runtime/bin/gsettings.exe
gstreamer_runtime-1.27.90.data/purelib/gstreamer_runtime/bin/gspawn-win64-helper-console.exe
gstreamer_runtime-1.27.90.data/purelib/gstreamer_runtime/bin/gspawn-win64-helper.exe
gstreamer_runtime-1.27.90.dist-info/METADATA
gstreamer_runtime-1.27.90.dist-info/WHEEL
gstreamer_runtime-1.27.90.dist-info/top_level.txt
gstreamer_runtime-1.27.90.dist-info/RECORD
