Metadata-Version: 2.4
Name: gstreamer_runtime
Version: 1.27.90
Summary: GStreamer 1.0
Home-page: http://gstreamer.freedesktop.org
Author: GStreamer Project
License: LGPL-2.1-or-later AND BSD-3-Clause AND bzip2-1.0.6 AND Libpng AND libtiff AND MPL-2.0 AND Zlib AND MPL-1.1 AND Apache-2.0 AND FTL AND GPL-2.0-or-later AND IJG AND Zlib AND BSD-3-Clause AND BSD-2-Clause AND MIT AND LGPL-2.0-or-later
Classifier: Development Status :: 4 - Beta
Classifier: Intended Audience :: Developers
Classifier: Programming Language :: Python :: 3
Classifier: Topic :: Multimedia :: Graphics
Classifier: Topic :: Multimedia :: Sound/Audio
Classifier: Topic :: Multimedia :: Video
Classifier: Topic :: Software Development
Classifier: Topic :: Utilities
Classifier: Environment :: MacOS X
Classifier: Operating System :: MacOS :: MacOS X
Classifier: Environment :: Win32 (MS Windows)
Classifier: Operating System :: Microsoft :: Windows
Requires-Python: >= 3.13
Requires-Dist: setuptools>=80.9.0
Requires-Dist: typing_extensions>=4.15.0
Requires-Dist: gstreamer_msvc_runtime~=1.27.90
Dynamic: author
Dynamic: classifier
Dynamic: home-page
Dynamic: license
Dynamic: requires-dist
Dynamic: requires-python
Dynamic: summary
